api_helper/__init__.py
api_helper/captcha.py
api_helper/client.py
api_helper/exceptions.py
api_helper/importers.py
api_helper/settings.py
api_helper/utils.py
cc_agent_helper-1.0.6.dist-info/METADATA
cc_agent_helper-1.0.6.dist-info/WHEEL
cc_agent_helper-1.0.6.dist-info/top_level.txt
cc_agent_helper-1.0.6.dist-info/RECORD
