Metadata-Version: 2.1
Name: cc-agent-helper
Version: 1.0.6
Summary: Agent Helper
Home-page: https://github.com/cockreative/cc-agent-helper
Author: Cockreative
Author-email: contact@cockreative.com
License: UNKNOWN
Project-URL: Bug Tracker, https://github.com/cockreative/cc-agent-helper/issues
Platform: UNKNOWN
Classifier: Programming Language :: Python :: 3
Classifier: License :: OSI Approved :: MIT License
Classifier: Operating System :: OS Independent
Requires-Python: >=3.8
Requires-Dist: beautifulsoup4
Requires-Dist: requests
